Workbook

Sheet RAW
A1: Invoice Number | B1: Quantity | C1: Retail Price | D1: Disc Description | E1: Selling Price | F1: Document Data | G1: Item Code | H1: Store of the document | I1: Document Index | J1: Disc - Tax excl. amount | K1: Disc - Tax excl. amount in currency | L1: Disc - Tax incl. amount | M1: Disc - Tax incl. amount in currency | N1: Disc line type | O1: Doc number | P1: Line number | Q1: Order Number | R1: Origin of discount | S1: Ranking number | T1: Line ranking number | U1: Disc percentage | V1: Disc line stub | W1: Disc basis | X1: Disc basis price - currency | Y1: Sales Condition | Z1: Item Identiier | AA1: Register of the line | AB1: Warehouse Doc | AC1: Store - document line | AD1: Brand | AE1: Dept | AF1: Segment | AG1: Countermark supplier | AH1: Line Description | AI1: Doc lin sales representative | AJ1: Third party of the line | AK1: Item type line | AL1: Type of line | AM1: Shipping status for items | AN1: Doc of consigned items | AO1: Vendor Style Code | AP1: Add item description | AQ1: Dimension | AR1: Develop code | AS1: Item barcode | AT1: Colour | AU1: Size | AV1: Dimension 3 | AW1: Dimension 4 | AX1: Dimension 5 | AY1: Promo Type
A2: 29057 | B2: 1 | C2: 1990000 | D2: Special Offer | E2: 1253700 | F2: 46292 | G2: FIRDA | H2: M310 | I2: 0 | J2: 125496 | K2: 125496 | L2: 139300 | M2: 139300 | N2: FFO | O2: 29057 | P2: 2 | Q2: 2 | R2: 006 | S2: 2 | T2: 0 | U2: 10 | V2: M310 | W2: 1393000 | X2: 1393000 | Y2: 7059 | Z2: FIRDA 003007 X | AB2: M310 | AC2: M310 | AD2: EB | AE2: LDS | AF2: SHS | AH2: EVERBEST LADIES SHOES BLACK 40 | AI2: 17294 | AJ2: WLK999 | AL2: ART | AO2: JZ | AS2: 996902067294 | AT2: 003 | AU2: 007 | AY2: ADD 10%
A3: 29057 | B3: 1 | C3: 1790000 | D3: Special Offer | E3: 1127700 | F3: 46292 | G3: DERBY | H3: M310 | I3: 0 | J3: 112883 | K3: 112883 | L3: 125300 | M3: 125300 | N3: FFO | O3: 29057 | P3: 1 | Q3: 1 | R3: 006 | S3: 2 | T3: 0 | U3: 10 | V3: M310 | W3: 1253000 | X3: 1253000 | Y3: 7059 | Z3: DERBY 001008 X | AB3: M310 | AC3: M310 | AD3: EB | AE3: LDS | AF3: SHS | AH3: EVERBEST LADIES SHOES ALMOND 39 | AI3: 17294 | AJ3: WLK999 | AL3: ART | AO3: JZ | AS3: 996902037700 | AT3: 001 | AU3: 008 | AY3: ADD 10%
A4: 29056 | B4: 1 | C4: 1690000 | D4: Special Offer | E4: 1064700 | F4: 46292 | G4: EFINE | H4: M310 | I4: 0 | J4: 106577 | K4: 106577 | L4: 118300 | M4: 118300 | N4: FFO | O4: 29056 | P4: 2 | Q4: 2 | R4: 006 | S4: 2 | T4: 0 | U4: 10 | V4: M310 | W4: 1183000 | X4: 1183000 | Y4: 7059 | Z4: EFINE 003001 X | AB4: M310 | AC4: M310 | AD4: EB | AE4: LDS | AF4: SHS | AH4: EVERBEST LADIES SHOES BLACK 37 | AI4: 17288 | AJ4: WLK999 | AL4: ART | AO4: KH | AS4: 996902079892 | AT4: 003 | AU4: 001 | AY4: ADD 10%
A5: 29056 | B5: 1 | C5: 1690000 | D5: Special Offer | E5: 1064700 | F5: 46292 | G5: EFINE | H5: M310 | I5: 0 | J5: 106577 | K5: 106577 | L5: 118300 | M5: 118300 | N5: FFO | O5: 29056 | P5: 1 | Q5: 1 | R5: 006 | S5: 2 | T5: 0 | U5: 10 | V5: M310 | W5: 1183000 | X5: 1183000 | Y5: 7059 | Z5: EFINE 00H005 X | AB5: M310 | AC5: M310 | AD5: EB | AE5: LDS | AF5: SHS | AH5: EVERBEST LADIES SHOES LIGHT BLUE 36 | AI5: 17288 | AJ5: WLK999 | AL5: ART | AO5: KH | AS5: 996902079898 | AT5: 00H | AU5: 005 | AY5: ADD 10%
A6: 29050 | B6: 1 | C6: 2990000 | D6: Special Offer | E6: 1345500 | F6: 46291 | G6: OLETHA | H6: M310 | I6: 0 | J6: 134685 | K6: 134685 | L6: 149500 | M6: 149500 | N6: FFO | O6: 29050 | P6: 1 | Q6: 1 | R6: 006 | S6: 2 | T6: 0 | U6: 10 | V6: M310 | W6: 1495000 | X6: 1495000 | Y6: 7059 | Z6: OLETHA 002001 X | AB6: M310 | AC6: M310 | AD6: EB | AE6: LDS | AF6: BAG | AH6: EVERBEST LADIES HANDBAGS BEIGE FREE SIZE | AI6: 17286 | AJ6: WLK999 | AL6: ART | AO6: HJX | AQ6: 25(L) x 105(H) x 25(W) cm | AS6: 996902072727 | AT6: 002 | AU6: 001 | AY6: ADD 10%
A7: 29050 | B7: 1 | C7: 2390000 | D7: Special Offer | E7: 1075500 | F7: 46291 | G7: OMYRA | H7: M310 | I7: 0 | J7: 107658 | K7: 107658 | L7: 119500 | M7: 119500 | N7: FFO | O7: 29050 | P7: 2 | Q7: 2 | R7: 006 | S7: 2 | T7: 0 | U7: 10 | V7: M310 | W7: 1195000 | X7: 1195000 | Y7: 7059 | Z7: OMYRA 003001 X | AB7: M310 | AC7: M310 | AD7: EB | AE7: LDS | AF7: BAG | AH7: EVERBEST LADIES HANDBAGS BLACK FREE SIZE | AI7: 17286 | AJ7: WLK999 | AL7: ART | AO7: HBYY | AQ7: 21(L) x 7(H) x 14(W) cm | AS7: 996902072729 | AT7: 003 | AU7: 001 | AY7: ADD 10%
A8: 29052 | B8: 1 | C8: 1890000 | D8: Special Offer | E8: 850500 | F8: 46291 | G8: LIVERA | H8: M310 | I8: 0 | J8: 85135 | K8: 85135 | L8: 94500 | M8: 94500 | N8: FFO | O8: 29052 | P8: 1 | Q8: 1 | R8: 006 | S8: 2 | T8: 0 | U8: 10 | V8: M310 | W8: 945000 | X8: 945000 | Y8: 7059 | Z8: LIVERA 003001 X | AB8: M310 | AC8: M310 | AD8: EB | AE8: LDS | AF8: SHS | AH8: EVERBEST LADIES SHOES BLACK 37 | AI8: 17288 | AJ8: WLK999 | AL8: ART | AO8: HU | AS8: 996902070742 | AT8: 003 | AU8: 001 | AY8: ADD 10%
A9: 29052 | B9: 1 | C9: 1790000 | D9: Special Offer | E9: 1127700 | F9: 46291 | G9: DERBY | H9: M310 | I9: 0 | J9: 112883 | K9: 112883 | L9: 125300 | M9: 125300 | N9: FFO | O9: 29052 | P9: 2 | Q9: 2 | R9: 006 | S9: 2 | T9: 0 | U9: 10 | V9: M310 | W9: 1253000 | X9: 1253000 | Y9: 7059 | Z9: DERBY 001002 X | AB9: M310 | AC9: M310 | AD9: EB | AE9: LDS | AF9: SHS | AH9: EVERBEST LADIES SHOES ALMOND 35 | AI9: 17288 | AJ9: WLK999 | AL9: ART | AO9: JZ | AS9: 996902037696 | AT9: 001 | AU9: 002 | AY9: ADD 10%
A10: 21891 | B10: 1 | C10: 1690000 | D10: Special Offer | E10: 718250 | F10: 46289 | G10: HANANIAH | H10: M010 | I10: 0 | J10: 114189 | K10: 114189 | L10: 126750 | M10: 126750 | N10: FFO | O10: 21891 | P10: 3 | Q10: 3 | R10: 006 | S10: 2 | T10: 0 | U10: 15 | V10: M010 | W10: 845000 | X10: 845000 | Y10: 7059 | Z10: HANANIAH 003003 X | AB10: M010 | AC10: M010 | AD10: EB | AE10: LDS | AF10: SHS | AH10: EVERBEST LADIES SHOES BLACK 38 | AI10: 15493 | AJ10: WLK999 | AL10: ART | AO10: BTN | AS10: 996902076124 | AT10: 003 | AU10: 003 | AY10: ADD 15%
A11: 21891 | B11: 1 | C11: 1890000 | D11: Special Offer | E11: 1124550 | F11: 46289 | G11: NAVELLA | H11: M010 | I11: 0 | J11: 178784 | K11: 178784 | L11: 198450 | M11: 198450 | N11: FFO | O11: 21891 | P11: 1 | Q11: 1 | R11: 006 | S11: 2 | T11: 0 | U11: 15 | V11: M010 | W11: 1323000 | X11: 1323000 | Y11: 7059 | Z11: NAVELLA 003002 X | AB11: M010 | AC11: M010 | AD11: EB | AE11: LDS | AF11: SHS | AH11: EVERBEST LADIES SHOES BLACK 35 | AI11: 15493 | AJ11: WLK999 | AL11: ART | AO11: HU | AS11: 996902081357 | AT11: 003 | AU11: 002 | AY11: ADD 15%
A12: 21891 | B12: 1 | C12: 1690000 | D12: Special Offer | E12: 718250 | F12: 46289 | G12: HANANIAH | H12: M010 | I12: 0 | J12: 114189 | K12: 114189 | L12: 126750 | M12: 126750 | N12: FFO | O12: 21891 | P12: 2 | Q12: 2 | R12: 006 | S12: 2 | T12: 0 | U12: 15 | V12: M010 | W12: 845000 | X12: 845000 | Y12: 7059 | Z12: HANANIAH 003001 X | AB12: M010 | AC12: M010 | AD12: EB | AE12: LDS | AF12: SHS | AH12: EVERBEST LADIES SHOES BLACK 37 | AI12: 15493 | AJ12: WLK999 | AL12: ART | AO12: BTN | AS12: 996902076123 | AT12: 003 | AU12: 001 | AY12: ADD 15%
A13: 21871 | B13: 1 | C13: 1790000 | D13: Special Offer | E13: 805500 | F13: 46285 | G13: NALANA | H13: M010 | I13: 0 | J13: 80631 | K13: 80631 | L13: 89500 | M13: 89500 | N13: FFO | O13: 21871 | P13: 2 | Q13: 2 | R13: 006 | S13: 2 | T13: 0 | U13: 10 | V13: M010 | W13: 895000 | X13: 895000 | Y13: 7059 | Z13: NALANA 002005 X | AB13: M010 | AC13: M010 | AD13: EB | AE13: LDS | AF13: SHS | AH13: EVERBEST LADIES SHOES BEIGE 36 | AI13: 16625 | AJ13: WLK999 | AL13: ART | AO13: HU | AS13: 996902073402 | AT13: 002 | AU13: 005 | AY13: ADD 10%
A14: 21871 | B14: 1 | C14: 1890000 | D14: Special Offer | E14: 1020600 | F14: 46285 | G14: JIANNI | H14: M010 | I14: 0 | J14: 102162 | K14: 102162 | L14: 113400 | M14: 113400 | N14: FFO | O14: 21871 | P14: 1 | Q14: 1 | R14: 006 | S14: 2 | T14: 0 | U14: 10 | V14: M010 | W14: 1134000 | X14: 1134000 | Y14: 7059 | Z14: JIANNI 005003 X | AB14: M010 | AC14: M010 | AD14: EB | AE14: LDS | AF14: SHS | AH14: EVERBEST LADIES SHOES BRONZE 38 | AI14: 16625 | AJ14: WLK999 | AL14: ART | AO14: HU | AS14: 996902069259 | AT14: 005 | AU14: 003 | AY14: ADD 10%
A15: 29028 | B15: 1 | C15: 1790000 | D15: Special Offer | E15: 805500 | F15: 46285 | G15: PATRINA | H15: M310 | I15: 0 | J15: 80631 | K15: 80631 | L15: 89500 | M15: 89500 | N15: FFO | O15: 29028 | P15: 2 | Q15: 2 | R15: 006 | S15: 2 | T15: 0 | U15: 10 | V15: M310 | W15: 895000 | X15: 895000 | Y15: 7059 | Z15: PATRINA 00M001 X | AB15: M310 | AC15: M310 | AD15: EB | AE15: LDS | AF15: SHS | AH15: EVERBEST LADIES SHOES LIGHT YELLOW 37 | AI15: 17294 | AJ15: WLK999 | AL15: ART | AO15: KH | AS15: 996902074117 | AT15: 00M | AU15: 001 | AY15: ADD 10%
A16: 36485 | B16: 1 | C16: 1890000 | D16: Special Offer | E16: 1190700 | F16: 46285 | G16: GAVESHA | H16: M730 | I16: 0 | J16: 119189 | K16: 119189 | L16: 132300 | M16: 132300 | N16: FFO | O16: 36485 | P16: 2 | Q16: 6 | R16: 006 | S16: 2 | T16: 0 | U16: 10 | V16: M730 | W16: 1323000 | X16: 1323000 | Y16: 7059 | Z16: GAVESHA 003001 X | AB16: M730 | AC16: M730 | AD16: EB | AE16: LDS | AF16: BAG | AH16: EVERBEST LADIES BAGS BLACK FREE SIZE | AI16: 17096 | AJ16: WLK999 | AL16: ART | AO16: HBYY | AS16: 996902081883 | AT16: 003 | AU16: 001 | AY16: ADD 10%
A17: 36485 | B17: 1 | C17: 2490000 | D17: Special Offer | E17: 1568700 | F17: 46285 | G17: INHA | H17: M730 | I17: 0 | J17: 157027 | K17: 157027 | L17: 174300 | M17: 174300 | N17: FFO | O17: 36485 | P17: 1 | Q17: 4 | R17: 006 | S17: 2 | T17: 0 | U17: 10 | V17: M730 | W17: 1743000 | X17: 1743000 | Y17: 7059 | Z17: INHA 003001 X | AB17: M730 | AC17: M730 | AD17: EB | AE17: LDS | AF17: BAG | AH17: EVERBEST LADIES BAGS BLACK FREE SIZE | AI17: 17096 | AJ17: WLK999 | AL17: ART | AS17: 996902080351 | AT17: 003 | AU17: 001 | AY17: ADD 10%
A18: 36489 | B18: 1 | C18: 1790000 | D18: Special Offer | E18: 760750 | F18: 46285 | G18: ARDERE | H18: M730 | I18: 0 | J18: 120946 | K18: 120946 | L18: 134250 | M18: 134250 | N18: FFO | O18: 36489 | P18: 2 | Q18: 2 | R18: 006 | S18: 2 | T18: 0 | U18: 15 | V18: M730 | W18: 895000 | X18: 895000 | Y18: 7059 | Z18: ARDERE 011008 X | AB18: M730 | AC18: M730 | AD18: EB | AE18: LDS | AF18: SHS | AH18: EVERBEST LADIES SHOES TAUPE 39 | AI18: 16927 | AJ18: WLK999 | AL18: ART | AO18: JZ | AS18: 996902071413 | AT18: 011 | AU18: 008 | AY18: ADD 15%
A19: 36489 | B19: 1 | C19: 1790000 | D19: Special Offer | E19: 760750 | F19: 46285 | G19: FURREY | H19: M730 | I19: 0 | J19: 120946 | K19: 120946 | L19: 134250 | M19: 134250 | N19: FFO | O19: 36489 | P19: 3 | Q19: 3 | R19: 006 | S19: 2 | T19: 0 | U19: 15 | V19: M730 | W19: 895000 | X19: 895000 | Y19: 7059 | Z19: FURREY 00Z005 X | AB19: M730 | AC19: M730 | AD19: EB | AE19: LDS | AF19: SHS | AH19: EVERBEST LADIES SHOES TAN 36 | AI19: 16927 | AJ19: WLK999 | AL19: ART | AO19: HU | AS19: 996902066782 | AT19: 00Z | AU19: 005 | AY19: ADD 15%
A20: 29013 | B20: 1 | C20: 1690000 | D20: Special Offer | E20: 912600 | F20: 46282 | G20: BRAYLEN | H20: M310 | I20: 0 | J20: 91351 | K20: 91351 | L20: 101400 | M20: 101400 | N20: FFO | O20: 29013 | P20: 1 | Q20: 1 | R20: 006 | S20: 2 | T20: 0 | U20: 10 | V20: M310 | W20: 1014000 | X20: 1014000 | Y20: 7059 | Z20: BRAYLEN 003007 X | AB20: M310 | AC20: M310 | AD20: EB | AE20: MEN | AF20: SHS | AH20: EVERBEST MEN SHOES BLACK 40 | AI20: 15443 | AJ20: WLK999 | AL20: ART | AO20: DB | AS20: 996902068024 | AT20: 003 | AU20: 007 | AY20: ADD 10%
A21: 36461 | B21: 1 | C21: 2290000 | D21: Special Offer | E21: 1442700 | F21: 46281 | G21: EFRA | H21: M730 | I21: 0 | J21: 144414 | K21: 144414 | L21: 160300 | M21: 160300 | N21: FFO | O21: 36461 | P21: 1 | Q21: 1 | R21: 006 | S21: 2 | T21: 0 | U21: 10 | V21: M730 | W21: 1603000 | X21: 1603000 | Y21: 7059 | Z21: EFRA 003001 X | AB21: M730 | AC21: M730 | AD21: EB | AE21: LDS | AF21: BAG | AH21: EVERBEST LADIES HANDBAGS BLACK FREE SIZE | AI21: 17170 | AJ21: WLK999 | AL21: ART | AS21: 996902078230 | AT21: 003 | AU21: 001 | AY21: ADD 10%
A22: 36457 | B22: 1 | C22: 1790000 | D22: Special Offer | E22: 805500 | F22: 46279 | G22: FERBIE | H22: M730 | I22: 0 | J22: 80631 | K22: 80631 | L22: 89500 | M22: 89500 | N22: FFO | O22: 36457 | P22: 2 | Q22: 2 | R22: 006 | S22: 2 | T22: 0 | U22: 10 | V22: M730 | W22: 895000 | X22: 895000 | Y22: 7059 | Z22: FERBIE 003005 X | AB22: M730 | AC22: M730 | AD22: EB | AE22: LDS | AF22: SHS | AH22: EVERBEST LADIES SHOES BLACK 36 | AI22: 16927 | AJ22: WLK999 | AL22: ART | AO22: JZ | AS22: 996902067566 | AT22: 003 | AU22: 005 | AY22: ADD 10%
A23: 36457 | B23: 1 | C23: 1790000 | D23: Special Offer | E23: 805500 | F23: 46279 | G23: FERBIE | H23: M730 | I23: 0 | J23: 80631 | K23: 80631 | L23: 89500 | M23: 89500 | N23: FFO | O23: 36457 | P23: 1 | Q23: 1 | R23: 006 | S23: 2 | T23: 0 | U23: 10 | V23: M730 | W23: 895000 | X23: 895000 | Y23: 7059 | Z23: FERBIE 003002 X | AB23: M730 | AC23: M730 | AD23: EB | AE23: LDS | AF23: SHS | AH23: EVERBEST LADIES SHOES BLACK 35 | AI23: 16927 | AJ23: WLK999 | AL23: ART | AO23: JZ | AS23: 996902067565 | AT23: 003 | AU23: 002 | AY23: ADD 10%
A24: 36447 | B24: 1 | C24: 1790000 | D24: Special Offer | E24: 1065050 | F24: 46277 | G24: MARCUS | H24: M730 | I24: 0 | J24: 169324 | K24: 169324 | L24: 187950 | M24: 187950 | N24: FFO | O24: 36447 | P24: 3 | Q24: 4 | R24: 006 | S24: 2 | T24: 0 | U24: 15 | V24: M730 | W24: 1253000 | X24: 1253000 | Y24: 7059 | Z24: MARCUS 00P001 X | AB24: M730 | AC24: M730 | AD24: EB | AE24: MEN | AF24: BAG | AH24: EVERBEST MEN BAGS NAVY FREE SIZE | AI24: 16927 | AJ24: WLK999 | AL24: ART | AO24: EVG | AS24: 996902053384 | AT24: 00P | AU24: 001 | AY24: ADD 15%
A25: 29006 | B25: 1 | C25: 2390000 | D25: Special Offer | E25: 1015750 | F25: 46277 | G25: OMYRA | H25: M310 | I25: 0 | J25: 161486 | K25: 161486 | L25: 179250 | M25: 179250 | N25: FFO | O25: 29006 | P25: 3 | Q25: 3 | R25: 006 | S25: 2 | T25: 0 | U25: 15 | V25: M310 | W25: 1195000 | X25: 1195000 | Y25: 7059 | Z25: OMYRA 002001 X | AB25: M310 | AC25: M310 | AD25: EB | AE25: LDS | AF25: BAG | AH25: EVERBEST LADIES HANDBAGS BEIGE FREE SIZE | AI25: 17286 | AJ25: WLK999 | AL25: ART | AO25: HBYY | AQ25: 21(L) x 7(H) x 14(W) cm | AS25: 996902072730 | AT25: 002 | AU25: 001 | AY25: ADD 15%
A26: 29006 | B26: 1 | C26: 1890000 | D26: Special Offer | E26: 803250 | F26: 46277 | G26: TYANNA | H26: M310 | I26: 0 | J26: 127703 | K26: 127703 | L26: 141750 | M26: 141750 | N26: FFO | O26: 29006 | P26: 1 | Q26: 1 | R26: 006 | S26: 2 | T26: 0 | U26: 15 | V26: M310 | W26: 945000 | X26: 945000 | Y26: 7059 | Z26: TYANNA 003003 X | AB26: M310 | AC26: M310 | AD26: EB | AE26: LDS | AF26: SHS | AH26: EVERBEST LADIES SHOES BLACK 38 | AI26: 17286 | AJ26: WLK999 | AL26: ART | AO26: JZ | AS26: 996902075042 | AT26: 003 | AU26: 003 | AY26: ADD 15%
A27: 36444 | B27: 1 | C27: 1990000 | D27: Special Offer | E27: 1184050 | F27: 46276 | G27: FIRDA | H27: M730 | I27: 0 | J27: 188243 | K27: 188243 | L27: 208950 | M27: 208950 | N27: FFO | O27: 36444 | P27: 3 | Q27: 3 | R27: 006 | S27: 2 | T27: 0 | U27: 15 | V27: M730 | W27: 1393000 | X27: 1393000 | Y27: 7059 | Z27: FIRDA 003002 X | AB27: M730 | AC27: M730 | AD27: EB | AE27: LDS | AF27: SHS | AH27: EVERBEST LADIES SHOES BLACK 35 | AI27: 16927 | AJ27: WLK999 | AL27: ART | AO27: JZ | AS27: 996902067289 | AT27: 003 | AU27: 002 | AY27: ADD 15%
A28: 36444 | B28: 1 | C28: 1690000 | D28: Special Offer | E28: 718250 | F28: 46276 | G28: MOSS | H28: M730 | I28: 0 | J28: 114189 | K28: 114189 | L28: 126750 | M28: 126750 | N28: FFO | O28: 36444 | P28: 1 | Q28: 1 | R28: 006 | S28: 2 | T28: 0 | U28: 15 | V28: M730 | W28: 845000 | X28: 845000 | Y28: 7059 | Z28: MOSS 003008 X | AB28: M730 | AC28: M730 | AD28: EB | AE28: MEN | AF28: SHS | AH28: EVERBEST MEN SHOES BLACK 39 | AI28: 16927 | AJ28: WLK999 | AL28: ART | AO28: SBL | AS28: 996902069191 | AT28: 003 | AU28: 008 | AY28: ADD 15%
A29: 29004 | B29: 1 | C29: 1890000 | D29: Special Offer | E29: 850500 | F29: 46276 | G29: NALI | H29: M310 | I29: 0 | J29: 85135 | K29: 85135 | L29: 94500 | M29: 94500 | N29: FFO | O29: 29004 | P29: 1 | Q29: 1 | R29: 006 | S29: 2 | T29: 0 | U29: 10 | V29: M310 | W29: 945000 | X29: 945000 | Y29: 7059 | Z29: NALI 002001 X | AB29: M310 | AC29: M310 | AD29: EB | AE29: LDS | AF29: SHS | AH29: EVERBEST LADIES SHOES BEIGE 37 | AI29: 17286 | AJ29: WLK999 | AL29: ART | AO29: HU | AS29: 996902073620 | AT29: 002 | AU29: 001 | AY29: ADD 10%
A30: 5420 | B30: 1 | C30: 1890000 | D30: Special Offer | E30: 1124550 | F30: 46275 | G30: GAVESHA | H30: M190 | I30: 0 | J30: 178784 | K30: 178784 | L30: 198450 | M30: 198450 | N30: FFO | O30: 5420 | P30: 6 | Q30: 6 | R30: 006 | S30: 2 | T30: 0 | U30: 15 | V30: M190 | W30: 1323000 | X30: 1323000 | Y30: 7059 | Z30: GAVESHA 001001 X | AB30: M190 | AC30: M190 | AD30: EB | AE30: LDS | AF30: BAG | AH30: EVERBEST LADIES BAGS ALMOND FREE SIZE | AI30: 15967 | AJ30: WLK999 | AL30: ART | AO30: HBYY | AS30: 996902081884 | AT30: 001 | AU30: 001 | AY30: ADD 15%
A31: 5420 | B31: 1 | C31: 1690000 | D31: Special Offer | E31: 1005550 | F31: 46275 | G31: CAILIN | H31: M190 | I31: 0 | J31: 159865 | K31: 159865 | L31: 177450 | M31: 177450 | N31: FFO | O31: 5420 | P31: 5 | Q31: 5 | R31: 006 | S31: 2 | T31: 0 | U31: 15 | V31: M190 | W31: 1183000 | X31: 1183000 | Y31: 7059 | Z31: CAILIN 003003 X | AB31: M190 | AC31: M190 | AD31: EB | AE31: LDS | AF31: SHS | AH31: EVERBEST LADIES SHOES BLACK 38 | AI31: 15967 | AJ31: WLK999 | AL31: ART | AO31: JZ | AS31: 996902079947 | AT31: 003 | AU31: 003 | AY31: ADD 15%
A32: 5420 | B32: 1 | C32: 1590000 | D32: Special Offer | E32: 675750 | F32: 46275 | G32: DANERA | H32: M190 | I32: 0 | J32: 107432 | K32: 107432 | L32: 119250 | M32: 119250 | N32: FFO | O32: 5420 | P32: 3 | Q32: 3 | R32: 006 | S32: 2 | T32: 0 | U32: 15 | V32: M190 | W32: 795000 | X32: 795000 | Y32: 7059 | Z32: DANERA 00P003 X | AB32: M190 | AC32: M190 | AD32: EB | AE32: LDS | AF32: SHS | AH32: EVERBEST LADIES SHOES NAVY 38 | AI32: 15967 | AJ32: WLK999 | AL32: ART | AO32: BTN | AS32: 996902064530 | AT32: 00P | AU32: 003 | AY32: ADD 15%
A33: 5420 | B33: 1 | C33: 1690000 | D33: Special Offer | E33: 718250 | F33: 46275 | G33: JASIC | H33: M190 | I33: 0 | J33: 114189 | K33: 114189 | L33: 126750 | M33: 126750 | N33: FFO | O33: 5420 | P33: 4 | Q33: 4 | R33: 006 | S33: 2 | T33: 0 | U33: 15 | V33: M190 | W33: 845000 | X33: 845000 | Y33: 7059 | Z33: JASIC 011001 X | AB33: M190 | AC33: M190 | AD33: EB | AE33: LDS | AF33: SHS | AH33: EVERBEST LADIES SHOES TAUPE 37 | AI33: 15967 | AJ33: WLK999 | AL33: ART | AO33: KH | AS33: 996902069471 | AT33: 011 | AU33: 001 | AY33: ADD 15%
A34: 5420 | B34: 1 | C34: 1690000 | D34: Special Offer | E34: 1005550 | F34: 46275 | G34: CESSEL | H34: M190 | I34: 0 | J34: 159865 | K34: 159865 | L34: 177450 | M34: 177450 | N34: FFO | O34: 5420 | P34: 2 | Q34: 2 | R34: 006 | S34: 2 | T34: 0 | U34: 15 | V34: M190 | W34: 1183000 | X34: 1183000 | Y34: 7059 | Z34: CESSEL 003001 X | AB34: M190 | AC34: M190 | AD34: EB | AE34: LDS | AF34: SHS | AH34: EVERBEST LADIES SHOES BLACK 37 | AI34: 15967 | AJ34: WLK999 | AL34: ART | AO34: JZ | AS34: 996902079780 | AT34: 003 | AU34: 001 | AY34: ADD 15%
A35: 5420 | B35: 1 | C35: 1690000 | D35: Special Offer | E35: 1005550 | F35: 46275 | G35: CESSEL | H35: M190 | I35: 0 | J35: 159865 | K35: 159865 | L35: 177450 | M35: 177450 | N35: FFO | O35: 5420 | P35: 1 | Q35: 1 | R35: 006 | S35: 2 | T35: 0 | U35: 15 | V35: M190 | W35: 1183000 | X35: 1183000 | Y35: 7059 | Z35: CESSEL 001005 X | AB35: M190 | AC35: M190 | AD35: EB | AE35: LDS | AF35: SHS | AH35: EVERBEST LADIES SHOES ALMOND 36 | AI35: 15967 | AJ35: WLK999 | AL35: ART | AO35: JZ | AS35: 996902079772 | AT35: 001 | AU35: 005 | AY35: ADD 15%
A36: 28989 | B36: 1 | C36: 1690000 | D36: Special Offer | E36: 1005550 | F36: 46274 | G36: NAHLA | H36: M310 | I36: 0 | J36: 159865 | K36: 159865 | L36: 177450 | M36: 177450 | N36: FFO | O36: 28989 | P36: 1 | Q36: 1 | R36: 006 | S36: 2 | T36: 0 | U36: 15 | V36: M310 | W36: 1183000 | X36: 1183000 | Y36: 7059 | Z36: NAHLA 003007 X | AB36: M310 | AC36: M310 | AD36: EB | AE36: LDS | AF36: SHS | AH36: EVERBEST LADIES SHOES BLACK 40 | AI36: 16281 | AJ36: WLK999 | AL36: ART | AO36: KH | AS36: 996902081341 | AT36: 003 | AU36: 007 | AY36: ADD 15%
A37: 28989 | B37: 1 | C37: 1690000 | D37: Special Offer | E37: 1005550 | F37: 46274 | G37: NAHLA | H37: M310 | I37: 0 | J37: 159865 | K37: 159865 | L37: 177450 | M37: 177450 | N37: FFO | O37: 28989 | P37: 2 | Q37: 2 | R37: 006 | S37: 2 | T37: 0 | U37: 15 | V37: M310 | W37: 1183000 | X37: 1183000 | Y37: 7059 | Z37: NAHLA 00Z007 X | AB37: M310 | AC37: M310 | AD37: EB | AE37: LDS | AF37: SHS | AH37: EVERBEST LADIES SHOES TAN 40 | AI37: 16281 | AJ37: WLK999 | AL37: ART | AO37: KH | AS37: 996902081355 | AT37: 00Z | AU37: 007 | AY37: ADD 15%
A38: 28995 | B38: -1 | C38: 2990000 | D38: Special Offer | E38: -1270750 | F38: 46274 | G38: OLETHA | H38: M310 | I38: 0 | J38: -202027 | K38: -202027 | L38: -224250 | M38: -224250 | N38: FFO | O38: 28995 | P38: 2 | Q38: 20 | R38: 006 | S38: 2 | T38: 0 | U38: 15 | V38: M310 | W38: -1495000 | X38: -1495000 | Y38: 7059 | Z38: OLETHA 002001 X | AB38: M310 | AC38: M310 | AD38: EB | AE38: LDS | AF38: BAG | AH38: EVERBEST LADIES HANDBAGS BEIGE FREE SIZE | AI38: 17286 | AJ38: WLK999 | AL38: ART | AO38: HJX | AQ38: 25(L) x 105(H) x 25(W) cm | AS38: 996902072727 | AT38: 002 | AU38: 001 | AY38: ADD 15%
A39: 5419 | B39: 1 | C39: 2290000 | D39: Special Offer | E39: 1442700 | F39: 46274 | G39: GECCA | H39: M190 | I39: 0 | J39: 144414 | K39: 144414 | L39: 160300 | M39: 160300 | N39: FFO | O39: 5419 | P39: 2 | Q39: 2 | R39: 006 | S39: 2 | T39: 0 | U39: 10 | V39: M190 | W39: 1603000 | X39: 1603000 | Y39: 7059 | Z39: GECCA 001001 X | AB39: M190 | AC39: M190 | AD39: EB | AE39: LDS | AF39: BAG | AH39: EVERBEST LADIES BAGS ALMOND FREE SIZE | AI39: 15967 | AJ39: WLK999 | AL39: ART | AO39: EVG | AS39: 996902081881 | AT39: 001 | AU39: 001 | AY39: ADD 10%
A40: 28988 | B40: 1 | C40: 1990000 | D40: Special Offer | E40: 1184050 | F40: 46274 | G40: GERENA | H40: M310 | I40: 0 | J40: 188243 | K40: 188243 | L40: 208950 | M40: 208950 | N40: FFO | O40: 28988 | P40: 3 | Q40: 22 | R40: 006 | S40: 2 | T40: 0 | U40: 15 | V40: M310 | W40: 1393000 | X40: 1393000 | Y40: 7059 | Z40: GERENA 003001 X | AB40: M310 | AC40: M310 | AD40: EB | AE40: LDS | AF40: BAG | AH40: EVERBEST LADIES BAGS BLACK FREE SIZE | AI40: 17286 | AJ40: WLK999 | AL40: ART | AO40: HBYY | AS40: 996902082098 | AT40: 003 | AU40: 001 | AY40: ADD 15%
A41: 28991 | B41: 1 | C41: 1590000 | D41: Special Offer | E41: 715500 | F41: 46274 | G41: TREACY | H41: M310 | I41: 0 | J41: 71622 | K41: 71622 | L41: 79500 | M41: 79500 | N41: FFO | O41: 28991 | P41: 2 | Q41: 2 | R41: 006 | S41: 2 | T41: 0 | U41: 10 | V41: M310 | W41: 795000 | X41: 795000 | Y41: 7059 | Z41: TREACY 003008 X | AB41: M310 | AC41: M310 | AD41: EB | AE41: LDS | AF41: SHS | AH41: EVERBEST LADIES SHOES BLACK 39 | AI41: 17286 | AJ41: WLK999 | AL41: ART | AO41: BTN | AS41: 996902075111 | AT41: 003 | AU41: 008 | AY41: ADD 10%
A42: 5419 | B42: 1 | C42: 2090000 | D42: Special Offer | E42: 1316700 | F42: 46274 | G42: GIASHA | H42: M190 | I42: 0 | J42: 131802 | K42: 131802 | L42: 146300 | M42: 146300 | N42: FFO | O42: 5419 | P42: 1 | Q42: 1 | R42: 006 | S42: 2 | T42: 0 | U42: 10 | V42: M190 | W42: 1463000 | X42: 1463000 | Y42: 7059 | Z42: GIASHA 00Z001 X | AB42: M190 | AC42: M190 | AD42: EB | AE42: LDS | AF42: BAG | AH42: EVERBEST LADIES BAGS TAN FREE SIZE | AI42: 15967 | AJ42: WLK999 | AL42: ART | AO42: EVG | AS42: 996902082104 | AT42: 00Z | AU42: 001 | AY42: ADD 10%
A43: 28988 | B43: 1 | C43: 1790000 | D43: Special Offer | E43: 1065050 | F43: 46274 | G43: RELUNA | H43: M310 | I43: 0 | J43: 169324 | K43: 169324 | L43: 187950 | M43: 187950 | N43: FFO | O43: 28988 | P43: 2 | Q43: 21 | R43: 006 | S43: 2 | T43: 0 | U43: 15 | V43: M310 | W43: 1253000 | X43: 1253000 | Y43: 7059 | Z43: RELUNA 003001 X | AB43: M310 | AC43: M310 | AD43: EB | AE43: LDS | AF43: BAG | AH43: EVERBEST LADIES BAGS BLACK FREE SIZE | AI43: 17286 | AJ43: WLK999 | AL43: ART | AS43: 996902080342 | AT43: 003 | AU43: 001 | AY43: ADD 15%
A44: 28991 | B44: 1 | C44: 1690000 | D44: Special Offer | E44: 1064700 | F44: 46274 | G44: FESSYA | H44: M310 | I44: 0 | J44: 106577 | K44: 106577 | L44: 118300 | M44: 118300 | N44: FFO | O44: 28991 | P44: 1 | Q44: 1 | R44: 006 | S44: 2 | T44: 0 | U44: 10 | V44: M310 | W44: 1183000 | X44: 1183000 | Y44: 7059 | Z44: FESSYA 00P003 X | AB44: M310 | AC44: M310 | AD44: EB | AE44: LDS | AF44: SHS | AH44: EVERBEST LADIES SHOES NAVY 38 | AI44: 17286 | AJ44: WLK999 | AL44: ART | AO44: JZ | AS44: 996902079844 | AT44: 00P | AU44: 003 | AY44: ADD 10%
A45: 28989 | B45: 1 | C45: 1690000 | D45: Special Offer | E45: 1005550 | F45: 46274 | G45: EFINE | H45: M310 | I45: 0 | J45: 159865 | K45: 159865 | L45: 177450 | M45: 177450 | N45: FFO | O45: 28989 | P45: 4 | Q45: 6 | R45: 006 | S45: 2 | T45: 0 | U45: 15 | V45: M310 | W45: 1183000 | X45: 1183000 | Y45: 7059 | Z45: EFINE 00H008 X | AB45: M310 | AC45: M310 | AD45: EB | AE45: LDS | AF45: SHS | AH45: EVERBEST LADIES SHOES LIGHT BLUE 39 | AI45: 16281 | AJ45: WLK999 | AL45: ART | AO45: KH | AS45: 996902079901 | AT45: 00H | AU45: 008 | AY45: ADD 15%
A46: 28995 | B46: -1 | C46: 1990000 | D46: Special Offer | E46: -1184050 | F46: 46274 | G46: GERENA | H46: M310 | I46: 0 | J46: -188243 | K46: -188243 | L46: -208950 | M46: -208950 | N46: FFO | O46: 28995 | P46: 4 | Q46: 22 | R46: 006 | S46: 2 | T46: 0 | U46: 15 | V46: M310 | W46: -1393000 | X46: -1393000 | Y46: 7059 | Z46: GERENA 003001 X | AB46: M310 | AC46: M310 | AD46: EB | AE46: LDS | AF46: BAG | AH46: EVERBEST LADIES BAGS BLACK FREE SIZE | AI46: 17286 | AJ46: WLK999 | AL46: ART | AO46: HBYY | AS46: 996902082098 | AT46: 003 | AU46: 001 | AY46: ADD 15%
A47: 28989 | B47: 1 | C47: 1690000 | D47: Special Offer | E47: 1005550 | F47: 46274 | G47: EFINE | H47: M310 | I47: 0 | J47: 159865 | K47: 159865 | L47: 177450 | M47: 177450 | N47: FFO | O47: 28989 | P47: 3 | Q47: 5 | R47: 006 | S47: 2 | T47: 0 | U47: 15 | V47: M310 | W47: 1183000 | X47: 1183000 | Y47: 7059 | Z47: EFINE 003008 X | AB47: M310 | AC47: M310 | AD47: EB | AE47: LDS | AF47: SHS | AH47: EVERBEST LADIES SHOES BLACK 39 | AI47: 16281 | AJ47: WLK999 | AL47: ART | AO47: KH | AS47: 996902079894 | AT47: 003 | AU47: 008 | AY47: ADD 15%
A48: 28995 | B48: -1 | C48: 1790000 | D48: Special Offer | E48: -1065050 | F48: 46274 | G48: RELUNA | H48: M310 | I48: 0 | J48: -169324 | K48: -169324 | L48: -187950 | M48: -187950 | N48: FFO | O48: 28995 | P48: 3 | Q48: 21 | R48: 006 | S48: 2 | T48: 0 | U48: 15 | V48: M310 | W48: -1253000 | X48: -1253000 | Y48: 7059 | Z48: RELUNA 003001 X | AB48: M310 | AC48: M310 | AD48: EB | AE48: LDS | AF48: BAG | AH48: EVERBEST LADIES BAGS BLACK FREE SIZE | AI48: 17286 | AJ48: WLK999 | AL48: ART | AS48: 996902080342 | AT48: 003 | AU48: 001 | AY48: ADD 15%
A49: 28990 | B49: 1 | C49: 1890000 | D49: Special Offer | E49: 850500 | F49: 46274 | G49: BELVEN | H49: M310 | I49: 0 | J49: 85135 | K49: 85135 | L49: 94500 | M49: 94500 | N49: FFO | O49: 28990 | P49: 1 | Q49: 1 | R49: 006 | S49: 2 | T49: 0 | U49: 10 | V49: M310 | W49: 945000 | X49: 945000 | Y49: 7059 | Z49: BELVEN 002002 X | AB49: M310 | AC49: M310 | AD49: EB | AE49: LDS | AF49: SHS | AH49: EVERBEST LADIES SHOES BEIGE 35 | AI49: 16281 | AJ49: WLK999 | AL49: ART | AO49: HU | AS49: 996902071444 | AT49: 002 | AU49: 002 | AY49: ADD 10%
A50: 28988 | B50: 1 | C50: 2990000 | D50: Special Offer | E50: 1270750 | F50: 46274 | G50: OLETHA | H50: M310 | I50: 0 | J50: 202027 | K50: 202027 | L50: 224250 | M50: 224250 | N50: FFO | O50: 28988 | P50: 1 | Q50: 20 | R50: 006 | S50: 2 | T50: 0 | U50: 15 | V50: M310 | W50: 1495000 | X50: 1495000 | Y50: 7059 | Z50: OLETHA 002001 X | AB50: M310 | AC50: M310 | AD50: EB | AE50: LDS | AF50: BAG | AH50: EVERBEST LADIES HANDBAGS BEIGE FREE SIZE | AI50: 17286 | AJ50: WLK999 | AL50: ART | AO50: HJX | AQ50: 25(L) x 105(H) x 25(W) cm | AS50: 996902072727 | AT50: 002 | AU50: 001 | AY50: ADD 15%
A51: 28990 | B51: 1 | C51: 1890000 | D51: Special Offer | E51: 850500 | F51: 46274 | G51: CECANIA | H51: M310 | I51: 0 | J51: 85135 | K51: 85135 | L51: 94500 | M51: 94500 | N51: FFO | O51: 28990 | P51: 2 | Q51: 2 | R51: 006 | S51: 2 | T51: 0 | U51: 10 | V51: M310 | W51: 945000 | X51: 945000 | Y51: 7059 | Z51: CECANIA 003001 X | AB51: M310 | AC51: M310 | AD51: EB | AE51: LDS | AF51: SHS | AH51: EVERBEST LADIES SHOES BLACK 37 | AI51: 16281 | AJ51: WLK999 | AL51: ART | AO51: HU | AS51: 996902075758 | AT51: 003 | AU51: 001 | AY51: ADD 10%
A52: 28983 | B52: 1 | C52: 1890000 | D52: Special Offer | E52: 850500 | F52: 46273 | G52: NIANNE | H52: M310 | I52: 0 | J52: 85135 | K52: 85135 | L52: 94500 | M52: 94500 | N52: FFO | O52: 28983 | P52: 2 | Q52: 2 | R52: 006 | S52: 2 | T52: 0 | U52: 10 | V52: M310 | W52: 945000 | X52: 945000 | Y52: 7059 | Z52: NIANNE 00500S X | AB52: M310 | AC52: M310 | AD52: EB | AE52: LDS | AF52: SHS | AH52: EVERBEST LADIES SHOES BRONZE 41 | AI52: 17286 | AJ52: WLK999 | AL52: ART | AO52: HU | AS52: 996902073673 | AT52: 005 | AU52: 00S | AY52: ADD 10%
A53: 28983 | B53: 1 | C53: 1890000 | D53: Special Offer | E53: 850500 | F53: 46273 | G53: NIANNE | H53: M310 | I53: 0 | J53: 85135 | K53: 85135 | L53: 94500 | M53: 94500 | N53: FFO | O53: 28983 | P53: 1 | Q53: 1 | R53: 006 | S53: 2 | T53: 0 | U53: 10 | V53: M310 | W53: 945000 | X53: 945000 | Y53: 7059 | Z53: NIANNE 00300S X | AB53: M310 | AC53: M310 | AD53: EB | AE53: LDS | AF53: SHS | AH53: EVERBEST LADIES SHOES BLACK 41 | AI53: 17286 | AJ53: WLK999 | AL53: ART | AO53: HU | AS53: 996902073666 | AT53: 003 | AU53: 00S | AY53: ADD 10%
A54: 28980 | B54: 1 | C54: 1990000 | D54: Special Offer | E54: 1253700 | F54: 46271 | G54: FIRDA | H54: M310 | I54: 0 | J54: 125496 | K54: 125496 | L54: 139300 | M54: 139300 | N54: FFO | O54: 28980 | P54: 2 | Q54: 2 | R54: 006 | S54: 2 | T54: 0 | U54: 10 | V54: M310 | W54: 1393000 | X54: 1393000 | Y54: 7059 | Z54: FIRDA 003002 X | AB54: M310 | AC54: M310 | AD54: EB | AE54: LDS | AF54: SHS | AH54: EVERBEST LADIES SHOES BLACK 35 | AI54: 16281 | AJ54: WLK999 | AL54: ART | AO54: JZ | AS54: 996902067289 | AT54: 003 | AU54: 002 | AY54: ADD 10%
A55: 28980 | B55: 1 | C55: 1690000 | D55: Special Offer | E55: 1064700 | F55: 46271 | G55: CESSEL | H55: M310 | I55: 0 | J55: 106577 | K55: 106577 | L55: 118300 | M55: 118300 | N55: FFO | O55: 28980 | P55: 1 | Q55: 1 | R55: 006 | S55: 2 | T55: 0 | U55: 10 | V55: M310 | W55: 1183000 | X55: 1183000 | Y55: 7059 | Z55: CESSEL 001005 X | AB55: M310 | AC55: M310 | AD55: EB | AE55: LDS | AF55: SHS | AH55: EVERBEST LADIES SHOES ALMOND 36 | AI55: 16281 | AJ55: WLK999 | AL55: ART | AO55: JZ | AS55: 996902079772 | AT55: 001 | AU55: 005 | AY55: ADD 10%
A56: 14250 | B56: 1 | C56: 2290000 | D56: Special Offer | E56: 1442700 | F56: 46270 | G56: EFRA | H56: M420 | I56: 0 | J56: 144414 | K56: 144414 | L56: 160300 | M56: 160300 | N56: FFO | O56: 14250 | P56: 1 | Q56: 1 | R56: 006 | S56: 2 | T56: 0 | U56: 10 | V56: M420 | W56: 1603000 | X56: 1603000 | Y56: 7059 | Z56: EFRA 003001 X | AB56: M420 | AC56: M420 | AD56: EB | AE56: LDS | AF56: BAG | AH56: EVERBEST LADIES HANDBAGS BLACK FREE SIZE | AI56: 17033 | AJ56: WLK999 | AL56: ART | AS56: 996902078230 | AT56: 003 | AU56: 001 | AY56: ADD 10%
A57: 36418 | B57: 1 | C57: 1990000 | D57: Special Offer | E57: 895500 | F57: 46270 | G57: PRIDDY | H57: M730 | I57: 0 | J57: 89640 | K57: 89640 | L57: 99500 | M57: 99500 | N57: FFO | O57: 36418 | P57: 1 | Q57: 13 | R57: 006 | S57: 2 | T57: 0 | U57: 10 | V57: M730 | W57: 995000 | X57: 995000 | Y57: 7059 | Z57: PRIDDY 003003 X | AB57: M730 | AC57: M730 | AD57: EB | AE57: LDS | AF57: SHS | AH57: EVERBEST LADIES SHOES BLACK 38 | AI57: 17170 | AJ57: WLK999 | AL57: ART | AO57: KH | AS57: 996902074090 | AT57: 003 | AU57: 003 | AY57: ADD 10%
A58: 36418 | B58: 1 | C58: 1990000 | D58: Special Offer | E58: 895500 | F58: 46270 | G58: PRIDDY | H58: M730 | I58: 0 | J58: 89640 | K58: 89640 | L58: 99500 | M58: 99500 | N58: FFO | O58: 36418 | P58: 2 | Q58: 14 | R58: 006 | S58: 2 | T58: 0 | U58: 10 | V58: M730 | W58: 995000 | X58: 995000 | Y58: 7059 | Z58: PRIDDY 00M001 X | AB58: M730 | AC58: M730 | AD58: EB | AE58: LDS | AF58: SHS | AH58: EVERBEST LADIES SHOES LIGHT YELLOW 37 | AI58: 17170 | AJ58: WLK999 | AL58: ART | AO58: KH | AS58: 996902074096 | AT58: 00M | AU58: 001 | AY58: ADD 10%
A59: 28976 | B59: 1 | C59: 1890000 | D59: Special Offer | E59: 803250 | F59: 46270 | G59: LIVERA | H59: M310 | I59: 0 | J59: 127703 | K59: 127703 | L59: 141750 | M59: 141750 | N59: FFO | O59: 28976 | P59: 4 | Q59: 38 | R59: 006 | S59: 2 | T59: 0 | U59: 15 | V59: M310 | W59: 945000 | X59: 945000 | Y59: 7059 | Z59: LIVERA 003003 X | AB59: M310 | AC59: M310 | AD59: EB | AE59: LDS | AF59: SHS | AH59: EVERBEST LADIES SHOES BLACK 38 | AI59: 15443 | AJ59: WLK999 | AL59: ART | AO59: HU | AS59: 996902070743 | AT59: 003 | AU59: 003 | AY59: ADD 15%
A60: 14250 | B60: 1 | C60: 1890000 | D60: Special Offer | E60: 1190700 | F60: 46270 | G60: GAVESHA | H60: M420 | I60: 0 | J60: 119189 | K60: 119189 | L60: 132300 | M60: 132300 | N60: FFO | O60: 14250 | P60: 2 | Q60: 2 | R60: 006 | S60: 2 | T60: 0 | U60: 10 | V60: M420 | W60: 1323000 | X60: 1323000 | Y60: 7059 | Z60: GAVESHA 00Z001 X | AB60: M420 | AC60: M420 | AD60: EB | AE60: LDS | AF60: BAG | AH60: EVERBEST LADIES BAGS TAN FREE SIZE | AI60: 17033 | AJ60: WLK999 | AL60: ART | AO60: HBYY | AS60: 996902081885 | AT60: 00Z | AU60: 001 | AY60: ADD 10%
A61: 28976 | B61: 1 | C61: 1890000 | D61: Special Offer | E61: 803250 | F61: 46270 | G61: LIVERA | H61: M310 | I61: 0 | J61: 127703 | K61: 127703 | L61: 141750 | M61: 141750 | N61: FFO | O61: 28976 | P61: 1 | Q61: 35 | R61: 006 | S61: 2 | T61: 0 | U61: 15 | V61: M310 | W61: 945000 | X61: 945000 | Y61: 7059 | Z61: LIVERA 003002 X | AB61: M310 | AC61: M310 | AD61: EB | AE61: LDS | AF61: SHS | AH61: EVERBEST LADIES SHOES BLACK 35 | AI61: 16281 | AJ61: WLK999 | AL61: ART | AO61: HU | AS61: 996902070740 | AT61: 003 | AU61: 002 | AY61: ADD 15%
A62: 28976 | B62: 1 | C62: 1790000 | D62: Special Offer | E62: 760750 | F62: 46270 | G62: NITIN | H62: M310 | I62: 0 | J62: 120946 | K62: 120946 | L62: 134250 | M62: 134250 | N62: FFO | O62: 28976 | P62: 2 | Q62: 36 | R62: 006 | S62: 2 | T62: 0 | U62: 15 | V62: M310 | W62: 895000 | X62: 895000 | Y62: 7059 | Z62: NITIN 002007 X | AB62: M310 | AC62: M310 | AD62: EB | AE62: LDS | AF62: SHS | AH62: EVERBEST LADIES SHOES BEIGE 40 | AI62: 16281 | AJ62: WLK999 | AL62: ART | AO62: JZ | AS62: 996902073714 | AT62: 002 | AU62: 007 | AY62: ADD 15%
A63: 5415 | B63: 1 | C63: 2490000 | D63: Special Offer | E63: 1568700 | F63: 46268 | G63: EVIRA | H63: M190 | I63: 0 | J63: 157027 | K63: 157027 | L63: 174300 | M63: 174300 | N63: FFO | O63: 5415 | P63: 1 | Q63: 1 | R63: 006 | S63: 2 | T63: 0 | U63: 10 | V63: M190 | W63: 1743000 | X63: 1743000 | Y63: 7059 | Z63: EVIRA 003001 X | AB63: M190 | AC63: M190 | AD63: EB | AE63: LDS | AF63: BAG | AH63: EVERBEST LADIES HANDBAGS BLACK FREE SIZE | AI63: 15967 | AJ63: WLK999 | AL63: ART | AO63: HBYY | AQ63: 43(L) x 11(H) x 29(W) cm | AS63: 996902078212 | AT63: 003 | AU63: 001 | AY63: ADD 10%
A64: 5415 | B64: 1 | C64: 1690000 | D64: Special Offer | E64: 760500 | F64: 46268 | G64: JASIC | H64: M190 | I64: 0 | J64: 76126 | K64: 76126 | L64: 84500 | M64: 84500 | N64: FFO | O64: 5415 | P64: 2 | Q64: 2 | R64: 006 | S64: 2 | T64: 0 | U64: 10 | V64: M190 | W64: 845000 | X64: 845000 | Y64: 7059 | Z64: JASIC 003007 X | AB64: M190 | AC64: M190 | AD64: EB | AE64: LDS | AF64: SHS | AH64: EVERBEST LADIES SHOES BLACK 40 | AI64: 15967 | AJ64: WLK999 | AL64: ART | AO64: KH | AS64: 996902069467 | AT64: 003 | AU64: 007 | AY64: ADD 10%

Sheet SUMMARY
A1: PROMO RESULT
A2: Kolom diskon: Qty = SUM(Quantity), Amount = SUM(Selling Price) per Store x Promo Type (sheet RAW). Total & LW Sales: penjualan brand per toko selama periode promo & periode LW (query sales toko).
A3: Jenis Promo: BUY2 ADD10%,BUY3 OR MORE ADD15% ON ALL D30-D50
A4: Store Code | B4: ADD 10% | D4: ADD 15% | F4: Total (2-30 Sep'26) | H4: Stock 1 Sep 2026 | I4: Sellthru | J4: Cont% | K4: LW Sales (29 Jul - 26 Agu'26) | M4: Growth%
B5: Qty | C5: Amount | D5: Qty | E5: Amount | F5: Qty | G5: Amount | K5: Qty | L5: Amount
A6: M010 | B6: =SUMIFS(RAW!$B$2:$B$64,RAW!$H$2:$H$64,$A6,RAW!$AY$2:$AY$64,B$4) | C6: =SUMIFS(RAW!$E$2:$E$64,RAW!$H$2:$H$64,$A6,RAW!$AY$2:$AY$64,B$4) | D6: =SUMIFS(RAW!$B$2:$B$64,RAW!$H$2:$H$64,$A6,RAW!$AY$2:$AY$64,D$4) | E6: =SUMIFS(RAW!$E$2:$E$64,RAW!$H$2:$H$64,$A6,RAW!$AY$2:$AY$64,D$4) | F6: 73 | G6: 102013850 | I6: =F6/H6 | J6: =F6/$F$11 | K6: 66 | L6: 91823000 | M6: =G6/L6-1
A7: M190 | B7: =SUMIFS(RAW!$B$2:$B$64,RAW!$H$2:$H$64,$A7,RAW!$AY$2:$AY$64,B$4) | C7: =SUMIFS(RAW!$E$2:$E$64,RAW!$H$2:$H$64,$A7,RAW!$AY$2:$AY$64,B$4) | D7: =SUMIFS(RAW!$B$2:$B$64,RAW!$H$2:$H$64,$A7,RAW!$AY$2:$AY$64,D$4) | E7: =SUMIFS(RAW!$E$2:$E$64,RAW!$H$2:$H$64,$A7,RAW!$AY$2:$AY$64,D$4) | F7: 41 | G7: 41296800 | I7: =F7/H7 | J7: =F7/$F$11 | K7: 42 | L7: 44551300 | M7: =G7/L7-1
A8: M310 | B8: =SUMIFS(RAW!$B$2:$B$64,RAW!$H$2:$H$64,$A8,RAW!$AY$2:$AY$64,B$4) | C8: =SUMIFS(RAW!$E$2:$E$64,RAW!$H$2:$H$64,$A8,RAW!$AY$2:$AY$64,B$4) | D8: =SUMIFS(RAW!$B$2:$B$64,RAW!$H$2:$H$64,$A8,RAW!$AY$2:$AY$64,D$4) | E8: =SUMIFS(RAW!$E$2:$E$64,RAW!$H$2:$H$64,$A8,RAW!$AY$2:$AY$64,D$4) | F8: 128 | G8: 156982850 | I8: =F8/H8 | J8: =F8/$F$11 | K8: 152 | L8: 213210150 | M8: =G8/L8-1
A9: M420 | B9: =SUMIFS(RAW!$B$2:$B$64,RAW!$H$2:$H$64,$A9,RAW!$AY$2:$AY$64,B$4) | C9: =SUMIFS(RAW!$E$2:$E$64,RAW!$H$2:$H$64,$A9,RAW!$AY$2:$AY$64,B$4) | D9: =SUMIFS(RAW!$B$2:$B$64,RAW!$H$2:$H$64,$A9,RAW!$AY$2:$AY$64,D$4) | E9: =SUMIFS(RAW!$E$2:$E$64,RAW!$H$2:$H$64,$A9,RAW!$AY$2:$AY$64,D$4) | F9: 17 | G9: 19532400 | I9: =F9/H9 | J9: =F9/$F$11 | K9: 62 | L9: 66235000 | M9: =G9/L9-1
A10: M730 | B10: =SUMIFS(RAW!$B$2:$B$64,RAW!$H$2:$H$64,$A10,RAW!$AY$2:$AY$64,B$4) | C10: =SUMIFS(RAW!$E$2:$E$64,RAW!$H$2:$H$64,$A10,RAW!$AY$2:$AY$64,B$4) | D10: =SUMIFS(RAW!$B$2:$B$64,RAW!$H$2:$H$64,$A10,RAW!$AY$2:$AY$64,D$4) | E10: =SUMIFS(RAW!$E$2:$E$64,RAW!$H$2:$H$64,$A10,RAW!$AY$2:$AY$64,D$4) | F10: 128 | G10: 221640150 | I10: =F10/H10 | J10: =F10/$F$11 | K10: 139 | L10: 244998700 | M10: =G10/L10-1
A11: GRAND TOTAL | B11: =SUM(B6:B10) | C11: =SUM(C6:C10) | D11: =SUM(D6:D10) | E11: =SUM(E6:E10) | F11: =SUM(F6:F10) | G11: =SUM(G6:G10) | H11: =SUM(H6:H10) | I11: =F11/H11 | J11: =1 | K11: =SUM(K6:K10) | L11: =SUM(L6:L10) | M11: =G11/L11-1
