Workbook

Sheet RAW
A1: Invoice Number | B1: Quantity | C1: Retail Price | D1: Disc Description | E1: Selling Price | F1: Document Data | G1: Item Code | H1: Store of the document | I1: Document Index | J1: Disc - Tax excl. amount | K1: Disc - Tax excl. amount in currency | L1: Disc - Tax incl. amount | M1: Disc - Tax incl. amount in currency | N1: Disc line type | O1: Doc number | P1: Line number | Q1: Order Number | R1: Origin of discount | S1: Ranking number | T1: Line ranking number | U1: Disc percentage | V1: Disc line stub | W1: Disc basis | X1: Disc basis price - currency | Y1: Sales Condition | Z1: Item Identiier | AA1: Register of the line | AB1: Warehouse Doc | AC1: Store - document line | AD1: Brand | AE1: Dept | AF1: Segment | AG1: Countermark supplier | AH1: Line Description | AI1: Doc lin sales representative | AJ1: Third party of the line | AK1: Item type line | AL1: Type of line | AM1: Shipping status for items | AN1: Doc of consigned items | AO1: Vendor Style Code | AP1: Add item description | AQ1: Dimension | AR1: Develop code | AS1: Item barcode | AT1: Colour | AU1: Size | AV1: Dimension 3 | AW1: Dimension 4 | AX1: Dimension 5
A2: 24709 | B2: 1 | C2: 1890000 | D2: Special Offer | E2: 0 | F2: 46284 | G2: GAVESHA | H2: E552 | I2: 0 | J2: 1702703 | K2: 1702703 | L2: 1890000 | M2: 1890000 | N2: FFO | O2: 24709 | P2: 3 | Q2: 3 | R2: 006 | S2: 1 | T2: 0 | U2: 100 | V2: E552 | W2: 1890000 | X2: 1890000 | Y2: 7093B | Z2: GAVESHA 001001 X | AB2: E552 | AC2: E552 | AD2: EB | AE2: LDS | AF2: BAG | AH2: EVERBEST LADIES BAGS ALMOND FREE SIZE | AI2: 16373 | AJ2: Q6UYY7967633 | AL2: ART | AO2: HBYY | AS2: 996902081884 | AT2: 001 | AU2: 001
A3: 24710 | B3: 1 | C3: 790000 | D3: Special Offer | E3: 0 | F3: 46284 | G3: REIGN | H3: E552 | I3: 0 | J3: 711712 | K3: 711712 | L3: 790000 | M3: 790000 | N3: FFO | O3: 24710 | P3: 2 | Q3: 2 | R3: 006 | S3: 1 | T3: 0 | U3: 100 | V3: E552 | W3: 790000 | X3: 790000 | Y3: 7093A | Z3: REIGN 001001 X | AB3: E552 | AC3: E552 | AD3: EB | AE3: LDS | AF3: SLG | AH3: EVERBEST LADIES LANYARD ALMOND FREE SIZE | AI3: 16563 | AJ3: 5YBGZ5967646 | AL3: ART | AO3: EVG | AQ3: 8.5(L) x 12.4(H) cm | AS3: 996902074595 | AT3: 001 | AU3: 001
A4: 28280 | B4: 1 | C4: 1890000 | D4: Special Offer | E4: 0 | F4: 46284 | G4: GAVESHA | H4: E630 | I4: 0 | J4: 1702703 | K4: 1702703 | L4: 1890000 | M4: 1890000 | N4: FFO | O4: 28280 | P4: 4 | Q4: 4 | R4: 006 | S4: 1 | T4: 0 | U4: 100 | V4: E630 | W4: 1890000 | X4: 1890000 | Y4: 7093B | Z4: GAVESHA 00Z001 X | AB4: E630 | AC4: E630 | AD4: EB | AE4: LDS | AF4: BAG | AH4: EVERBEST LADIES BAGS TAN FREE SIZE | AI4: 17283 | AJ4: 8X16IS967678 | AL4: ART | AO4: HBYY | AS4: 996902081885 | AT4: 00Z | AU4: 001
A5: 53165 | B5: 1 | C5: 1890000 | D5: Special Offer | E5: 0 | F5: 46284 | G5: GAVESHA | H5: E820 | I5: 0 | J5: 1702703 | K5: 1702703 | L5: 1890000 | M5: 1890000 | N5: FFO | O5: 53165 | P5: 3 | Q5: 3 | R5: 006 | S5: 1 | T5: 0 | U5: 100 | V5: E820 | W5: 1890000 | X5: 1890000 | Y5: 7093B | Z5: GAVESHA 00Z001 X | AB5: E820 | AC5: E820 | AD5: EB | AE5: LDS | AF5: BAG | AH5: EVERBEST LADIES BAGS TAN FREE SIZE | AI5: 17100 | AJ5: PBFZ6G967597 | AL5: ART | AO5: HBYY | AS5: 996902081885 | AT5: 00Z | AU5: 001
A6: 53168 | B6: 1 | C6: 1890000 | D6: Special Offer | E6: 0 | F6: 46284 | G6: GAVESHA | H6: E820 | I6: 0 | J6: 1702703 | K6: 1702703 | L6: 1890000 | M6: 1890000 | N6: FFO | O6: 53168 | P6: 3 | Q6: 3 | R6: 006 | S6: 1 | T6: 0 | U6: 100 | V6: E820 | W6: 1890000 | X6: 1890000 | Y6: 7093B | Z6: GAVESHA 003001 X | AB6: E820 | AC6: E820 | AD6: EB | AE6: LDS | AF6: BAG | AH6: EVERBEST LADIES BAGS BLACK FREE SIZE | AI6: 17138 | AJ6: CONCK3967656 | AL6: ART | AO6: HBYY | AS6: 996902081883 | AT6: 003 | AU6: 001
A7: 15471 | B7: 1 | C7: 790000 | D7: Special Offer | E7: 0 | F7: 46284 | G7: REIGN | H7: E815 | I7: 0 | J7: 711712 | K7: 711712 | L7: 790000 | M7: 790000 | N7: FFO | O7: 15471 | P7: 2 | Q7: 2 | R7: 006 | S7: 1 | T7: 0 | U7: 100 | V7: E815 | W7: 790000 | X7: 790000 | Y7: 7093A | Z7: REIGN 002001 X | AB7: E815 | AC7: E815 | AD7: EB | AE7: LDS | AF7: SLG | AH7: EVERBEST LADIES LANYARD BEIGE FREE SIZE | AI7: 15108 | AJ7: AAGL0Z926163 | AL7: ART | AO7: EVG | AQ7: 8.5(L) x 12.4(H) cm | AS7: 996902074596 | AT7: 002 | AU7: 001
A8: 40279 | B8: 1 | C8: 1890000 | D8: Special Offer | E8: 0 | F8: 46284 | G8: GAVESHA | H8: E880 | I8: 0 | J8: 1702703 | K8: 1702703 | L8: 1890000 | M8: 1890000 | N8: FFO | O8: 40279 | P8: 3 | Q8: 7 | R8: 006 | S8: 1 | T8: 0 | U8: 100 | V8: E880 | W8: 1890000 | X8: 1890000 | Y8: 7093B | Z8: GAVESHA 003001 X | AB8: E880 | AC8: E880 | AD8: EB | AE8: LDS | AF8: BAG | AH8: EVERBEST LADIES BAGS BLACK FREE SIZE | AI8: 16265 | AJ8: ADA5OI967570 | AL8: ART | AO8: HBYY | AS8: 996902081883 | AT8: 003 | AU8: 001
A9: 40283 | B9: 1 | C9: 1890000 | D9: Special Offer | E9: 0 | F9: 46284 | G9: GAVESHA | H9: E880 | I9: 0 | J9: 1702703 | K9: 1702703 | L9: 1890000 | M9: 1890000 | N9: FFO | O9: 40283 | P9: 3 | Q9: 3 | R9: 006 | S9: 1 | T9: 0 | U9: 100 | V9: E880 | W9: 1890000 | X9: 1890000 | Y9: 7093B | Z9: GAVESHA 001001 X | AB9: E880 | AC9: E880 | AD9: EB | AE9: LDS | AF9: BAG | AH9: EVERBEST LADIES BAGS ALMOND FREE SIZE | AI9: 16676 | AJ9: Q8MGA6967591 | AL9: ART | AO9: HBYY | AS9: 996902081884 | AT9: 001 | AU9: 001
A10: 2444 | B10: 1 | C10: 1890000 | D10: Special Offer | E10: 0 | F10: 46284 | G10: GAVESHA | H10: E425 | I10: 0 | J10: 1702703 | K10: 1702703 | L10: 1890000 | M10: 1890000 | N10: FFO | O10: 2444 | P10: 3 | Q10: 3 | R10: 006 | S10: 1 | T10: 0 | U10: 100 | V10: E425 | W10: 1890000 | X10: 1890000 | Y10: 7093B | Z10: GAVESHA 003001 X | AB10: E425 | AC10: E425 | AD10: EB | AE10: LDS | AF10: BAG | AH10: EVERBEST LADIES BAGS BLACK FREE SIZE | AI10: 15432 | AJ10: 88EKW0967649 | AL10: ART | AO10: HBYY | AS10: 996902081883 | AT10: 003 | AU10: 001
A11: 35643 | B11: 1 | C11: 1890000 | D11: Special Offer | E11: 0 | F11: 46284 | G11: GAVESHA | H11: E450 | I11: 0 | J11: 1702703 | K11: 1702703 | L11: 1890000 | M11: 1890000 | N11: FFO | O11: 35643 | P11: 5 | Q11: 10 | R11: 006 | S11: 1 | T11: 0 | U11: 100 | V11: E450 | W11: 1890000 | X11: 1890000 | Y11: 7093B | Z11: GAVESHA 001001 X | AB11: E450 | AC11: E450 | AD11: EB | AE11: LDS | AF11: BAG | AH11: EVERBEST LADIES BAGS ALMOND FREE SIZE | AI11: 15777 | AJ11: YFN0WD324862 | AL11: ART | AO11: HBYY | AS11: 996902081884 | AT11: 001 | AU11: 001
A12: 3647 | B12: 1 | C12: 790000 | D12: Special Offer | E12: 0 | F12: 46284 | G12: REIGN | H12: E640 | I12: 0 | J12: 711712 | K12: 711712 | L12: 790000 | M12: 790000 | N12: FFO | O12: 3647 | P12: 2 | Q12: 2 | R12: 006 | S12: 1 | T12: 0 | U12: 100 | V12: E640 | W12: 790000 | X12: 790000 | Y12: 7093A | Z12: REIGN 003001 X | AB12: E640 | AC12: E640 | AD12: EB | AE12: LDS | AF12: SLG | AH12: EVERBEST LADIES LANYARD BLACK FREE SIZE | AI12: 15588 | AJ12: DTDIIK354152 | AL12: ART | AO12: EVG | AQ12: 8.5(L) x 12.4(H) cm | AS12: 996902074255 | AT12: 003 | AU12: 001
A13: 3649 | B13: 1 | C13: 790000 | D13: Special Offer | E13: 0 | F13: 46284 | G13: REIGN | H13: E640 | I13: 0 | J13: 711712 | K13: 711712 | L13: 790000 | M13: 790000 | N13: FFO | O13: 3649 | P13: 2 | Q13: 2 | R13: 006 | S13: 1 | T13: 0 | U13: 100 | V13: E640 | W13: 790000 | X13: 790000 | Y13: 7093A | Z13: REIGN 001001 X | AB13: E640 | AC13: E640 | AD13: EB | AE13: LDS | AF13: SLG | AH13: EVERBEST LADIES LANYARD ALMOND FREE SIZE | AI13: 17254 | AJ13: 63MYOX899931 | AL13: ART | AO13: EVG | AQ13: 8.5(L) x 12.4(H) cm | AS13: 996902074595 | AT13: 001 | AU13: 001
A14: 42956 | B14: 1 | C14: 1890000 | D14: Special Offer | E14: 0 | F14: 46284 | G14: GAVESHA | H14: E460 | I14: 0 | J14: 1702703 | K14: 1702703 | L14: 1890000 | M14: 1890000 | N14: FFO | O14: 42956 | P14: 2 | Q14: 2 | R14: 006 | S14: 1 | T14: 0 | U14: 100 | V14: E460 | W14: 1890000 | X14: 1890000 | Y14: 7093B | Z14: GAVESHA 003001 X | AB14: E460 | AC14: E460 | AD14: EB | AE14: LDS | AF14: BAG | AH14: EVERBEST LADIES BAGS BLACK FREE SIZE | AI14: 15873 | AJ14: 6YZ1AM943589 | AL14: ART | AO14: HBYY | AS14: 996902081883 | AT14: 003 | AU14: 001
A15: 49782 | B15: 1 | C15: 1890000 | D15: Special Offer | E15: 0 | F15: 46284 | G15: GAVESHA | H15: E850 | I15: 0 | J15: 1702703 | K15: 1702703 | L15: 1890000 | M15: 1890000 | N15: FFO | O15: 49782 | P15: 3 | Q15: 3 | R15: 006 | S15: 1 | T15: 0 | U15: 100 | V15: E850 | W15: 1890000 | X15: 1890000 | Y15: 7093B | Z15: GAVESHA 001001 X | AB15: E850 | AC15: E850 | AD15: EB | AE15: LDS | AF15: BAG | AH15: EVERBEST LADIES BAGS ALMOND FREE SIZE | AI15: 16696 | AJ15: DBYBS1499322 | AL15: ART | AO15: HBYY | AS15: 996902081884 | AT15: 001 | AU15: 001
A16: 5682 | B16: 1 | C16: 790000 | D16: Special Offer | E16: 0 | F16: 46284 | G16: REIGN | H16: E942 | I16: 0 | J16: 711712 | K16: 711712 | L16: 790000 | M16: 790000 | N16: FFO | O16: 5682 | P16: 2 | Q16: 2 | R16: 006 | S16: 1 | T16: 0 | U16: 100 | V16: E942 | W16: 790000 | X16: 790000 | Y16: 7093A | Z16: REIGN 002001 X | AB16: E942 | AC16: E942 | AD16: EB | AE16: LDS | AF16: SLG | AH16: EVERBEST LADIES LANYARD BEIGE FREE SIZE | AI16: 17141 | AJ16: RSAQK6920618 | AL16: ART | AO16: EVG | AQ16: 8.5(L) x 12.4(H) cm | AS16: 996902074596 | AT16: 002 | AU16: 001
A17: 5684 | B17: 1 | C17: 790000 | D17: Special Offer | E17: 0 | F17: 46284 | G17: REIGN | H17: E942 | I17: 0 | J17: 711712 | K17: 711712 | L17: 790000 | M17: 790000 | N17: FFO | O17: 5684 | P17: 4 | Q17: 7 | R17: 006 | S17: 1 | T17: 0 | U17: 100 | V17: E942 | W17: 790000 | X17: 790000 | Y17: 7093A | Z17: REIGN 002001 X | AB17: E942 | AC17: E942 | AD17: EB | AE17: LDS | AF17: SLG | AH17: EVERBEST LADIES LANYARD BEIGE FREE SIZE | AI17: 15205 | AJ17: RPWEHB967666 | AL17: ART | AO17: EVG | AQ17: 8.5(L) x 12.4(H) cm | AS17: 996902074596 | AT17: 002 | AU17: 001
A18: 45598 | B18: 1 | C18: 790000 | D18: Special Offer | E18: 0 | F18: 46284 | G18: REIGN | H18: E560 | I18: 0 | J18: 711712 | K18: 711712 | L18: 790000 | M18: 790000 | N18: FFO | O18: 45598 | P18: 2 | Q18: 2 | R18: 006 | S18: 1 | T18: 0 | U18: 100 | V18: E560 | W18: 790000 | X18: 790000 | Y18: 7093A | Z18: REIGN 001001 X | AB18: E560 | AC18: E560 | AD18: EB | AE18: LDS | AF18: SLG | AH18: EVERBEST LADIES LANYARD ALMOND FREE SIZE | AI18: 17068 | AJ18: G114K4967588 | AL18: ART | AO18: EVG | AQ18: 8.5(L) x 12.4(H) cm | AS18: 996902074595 | AT18: 001 | AU18: 001
A19: 45602 | B19: 1 | C19: 790000 | D19: Special Offer | E19: 0 | F19: 46284 | G19: REIGN | H19: E560 | I19: 0 | J19: 711712 | K19: 711712 | L19: 790000 | M19: 790000 | N19: FFO | O19: 45602 | P19: 1 | Q19: 5 | R19: 006 | S19: 1 | T19: 0 | U19: 100 | V19: E560 | W19: 790000 | X19: 790000 | Y19: 7093A | Z19: REIGN 002001 X | AB19: E560 | AC19: E560 | AD19: EB | AE19: LDS | AF19: SLG | AH19: EVERBEST LADIES LANYARD BEIGE FREE SIZE | AI19: 17328 | AJ19: 6TDF70903691 | AL19: ART | AO19: EVG | AQ19: 8.5(L) x 12.4(H) cm | AS19: 996902074596 | AT19: 002 | AU19: 001
A20: 45604 | B20: 1 | C20: 790000 | D20: Special Offer | E20: 0 | F20: 46284 | G20: REIGN | H20: E560 | I20: 0 | J20: 711712 | K20: 711712 | L20: 790000 | M20: 790000 | N20: FFO | O20: 45604 | P20: 2 | Q20: 2 | R20: 006 | S20: 1 | T20: 0 | U20: 100 | V20: E560 | W20: 790000 | X20: 790000 | Y20: 7093A | Z20: REIGN 002001 X | AB20: E560 | AC20: E560 | AD20: EB | AE20: LDS | AF20: SLG | AH20: EVERBEST LADIES LANYARD BEIGE FREE SIZE | AI20: 17068 | AJ20: O1L751837789 | AL20: ART | AO20: EVG | AQ20: 8.5(L) x 12.4(H) cm | AS20: 996902074596 | AT20: 002 | AU20: 001
A21: 45605 | B21: 1 | C21: 790000 | D21: Special Offer | E21: 0 | F21: 46284 | G21: REIGN | H21: E560 | I21: 0 | J21: 711712 | K21: 711712 | L21: 790000 | M21: 790000 | N21: FFO | O21: 45605 | P21: 2 | Q21: 2 | R21: 006 | S21: 1 | T21: 0 | U21: 100 | V21: E560 | W21: 790000 | X21: 790000 | Y21: 7093A | Z21: REIGN 001001 X | AB21: E560 | AC21: E560 | AD21: EB | AE21: LDS | AF21: SLG | AH21: EVERBEST LADIES LANYARD ALMOND FREE SIZE | AI21: 15770 | AJ21: 9VADVO709516 | AL21: ART | AO21: EVG | AQ21: 8.5(L) x 12.4(H) cm | AS21: 996902074595 | AT21: 001 | AU21: 001
A22: 38029 | B22: 1 | C22: 790000 | D22: Special Offer | E22: 0 | F22: 46284 | G22: REIGN | H22: E950 | I22: 0 | J22: 711712 | K22: 711712 | L22: 790000 | M22: 790000 | N22: FFO | O22: 38029 | P22: 2 | Q22: 3 | R22: 006 | S22: 1 | T22: 0 | U22: 100 | V22: E950 | W22: 790000 | X22: 790000 | Y22: 7093A | Z22: REIGN 003001 X | AB22: E950 | AC22: E950 | AD22: EB | AE22: LDS | AF22: SLG | AH22: EVERBEST LADIES LANYARD BLACK FREE SIZE | AI22: 16558 | AJ22: T950200000218 | AL22: ART | AO22: EVG | AQ22: 8.5(L) x 12.4(H) cm | AS22: 996902074255 | AT22: 003 | AU22: 001
A23: 38031 | B23: 1 | C23: 790000 | D23: Special Offer | E23: 0 | F23: 46284 | G23: REIGN | H23: E950 | I23: 0 | J23: 711712 | K23: 711712 | L23: 790000 | M23: 790000 | N23: FFO | O23: 38031 | P23: 2 | Q23: 2 | R23: 006 | S23: 1 | T23: 0 | U23: 100 | V23: E950 | W23: 790000 | X23: 790000 | Y23: 7093A | Z23: REIGN 001001 X | AB23: E950 | AC23: E950 | AD23: EB | AE23: LDS | AF23: SLG | AH23: EVERBEST LADIES LANYARD ALMOND FREE SIZE | AI23: 16558 | AJ23: LOA1OO967626 | AL23: ART | AO23: EVG | AQ23: 8.5(L) x 12.4(H) cm | AS23: 996902074595 | AT23: 001 | AU23: 001
A24: 38032 | B24: 1 | C24: 790000 | D24: Special Offer | E24: 0 | F24: 46284 | G24: REIGN | H24: E950 | I24: 0 | J24: 711712 | K24: 711712 | L24: 790000 | M24: 790000 | N24: FFO | O24: 38032 | P24: 2 | Q24: 2 | R24: 006 | S24: 1 | T24: 0 | U24: 100 | V24: E950 | W24: 790000 | X24: 790000 | Y24: 7093A | Z24: REIGN 003001 X | AB24: E950 | AC24: E950 | AD24: EB | AE24: LDS | AF24: SLG | AH24: EVERBEST LADIES LANYARD BLACK FREE SIZE | AI24: 15905 | AJ24: G1O3CI967629 | AL24: ART | AO24: EVG | AQ24: 8.5(L) x 12.4(H) cm | AS24: 996902074255 | AT24: 003 | AU24: 001
A25: 38033 | B25: 1 | C25: 1890000 | D25: Special Offer | E25: 0 | F25: 46284 | G25: GAVESHA | H25: E950 | I25: 0 | J25: 1702703 | K25: 1702703 | L25: 1890000 | M25: 1890000 | N25: FFO | O25: 38033 | P25: 3 | Q25: 3 | R25: 006 | S25: 1 | T25: 0 | U25: 100 | V25: E950 | W25: 1890000 | X25: 1890000 | Y25: 7093B | Z25: GAVESHA 003001 X | AB25: E950 | AC25: E950 | AD25: EB | AE25: LDS | AF25: BAG | AH25: EVERBEST LADIES BAGS BLACK FREE SIZE | AI25: 15164 | AJ25: JXN9IU967631 | AL25: ART | AO25: HBYY | AS25: 996902081883 | AT25: 003 | AU25: 001
A26: 38034 | B26: 1 | C26: 1890000 | D26: Special Offer | E26: 0 | F26: 46284 | G26: GAVESHA | H26: E950 | I26: 0 | J26: 1702703 | K26: 1702703 | L26: 1890000 | M26: 1890000 | N26: FFO | O26: 38034 | P26: 3 | Q26: 3 | R26: 006 | S26: 1 | T26: 0 | U26: 100 | V26: E950 | W26: 1890000 | X26: 1890000 | Y26: 7093B | Z26: GAVESHA 00Z001 X | AB26: E950 | AC26: E950 | AD26: EB | AE26: LDS | AF26: BAG | AH26: EVERBEST LADIES BAGS TAN FREE SIZE | AI26: 16362 | AJ26: ZVJTEH967628 | AL26: ART | AO26: HBYY | AS26: 996902081885 | AT26: 00Z | AU26: 001
A27: 29626 | B27: 1 | C27: 1890000 | D27: Special Offer | E27: 0 | F27: 46284 | G27: GAVESHA | H27: E105 | I27: 0 | J27: 1702703 | K27: 1702703 | L27: 1890000 | M27: 1890000 | N27: FFO | O27: 29626 | P27: 3 | Q27: 3 | R27: 006 | S27: 1 | T27: 0 | U27: 100 | V27: E105 | W27: 1890000 | X27: 1890000 | Y27: 7093B | Z27: GAVESHA 001001 X | AB27: E105 | AC27: E105 | AD27: EB | AE27: LDS | AF27: BAG | AH27: EVERBEST LADIES BAGS ALMOND FREE SIZE | AI27: 17197 | AJ27: O2N0ZI545212 | AL27: ART | AO27: HBYY | AS27: 996902081884 | AT27: 001 | AU27: 001
A28: 35217 | B28: 1 | C28: 1890000 | D28: Special Offer | E28: 0 | F28: 46284 | G28: GAVESHA | H28: E310 | I28: 0 | J28: 1702703 | K28: 1702703 | L28: 1890000 | M28: 1890000 | N28: FFO | O28: 35217 | P28: 2 | Q28: 2 | R28: 006 | S28: 1 | T28: 0 | U28: 100 | V28: E310 | W28: 1890000 | X28: 1890000 | Y28: 7093B | Z28: GAVESHA 00Z001 X | AB28: E310 | AC28: E310 | AD28: EB | AE28: LDS | AF28: BAG | AH28: EVERBEST LADIES BAGS TAN FREE SIZE | AI28: 15250 | AJ28: S5OKKA553217 | AL28: ART | AO28: HBYY | AS28: 996902081885 | AT28: 00Z | AU28: 001
A29: 57663 | B29: 1 | C29: 1890000 | D29: Special Offer | E29: 0 | F29: 46284 | G29: GAVESHA | H29: E810 | I29: 0 | J29: 1702703 | K29: 1702703 | L29: 1890000 | M29: 1890000 | N29: FFO | O29: 57663 | P29: 3 | Q29: 5 | R29: 006 | S29: 1 | T29: 0 | U29: 100 | V29: E810 | W29: 1890000 | X29: 1890000 | Y29: 7093B | Z29: GAVESHA 001001 X | AB29: E810 | AC29: E810 | AD29: EB | AE29: LDS | AF29: BAG | AH29: EVERBEST LADIES BAGS ALMOND FREE SIZE | AI29: 16991 | AJ29: W9NBZA967645 | AL29: ART | AO29: HBYY | AS29: 996902081884 | AT29: 001 | AU29: 001
A30: 57664 | B30: 1 | C30: 1890000 | D30: Special Offer | E30: 0 | F30: 46284 | G30: GAVESHA | H30: E810 | I30: 0 | J30: 1702703 | K30: 1702703 | L30: 1890000 | M30: 1890000 | N30: FFO | O30: 57664 | P30: 3 | Q30: 3 | R30: 006 | S30: 1 | T30: 0 | U30: 100 | V30: E810 | W30: 1890000 | X30: 1890000 | Y30: 7093B | Z30: GAVESHA 001001 X | AB30: E810 | AC30: E810 | AD30: EB | AE30: LDS | AF30: BAG | AH30: EVERBEST LADIES BAGS ALMOND FREE SIZE | AI30: 17152 | AJ30: 1SPSAP967674 | AL30: ART | AO30: HBYY | AS30: 996902081884 | AT30: 001 | AU30: 001

Sheet SUMMARY
A1: PROMO RESULT
A2: Kolom diskon: Qty = SUM(Quantity), Amount = SUM(Selling Price) per Store x Disc Description (sheet RAW). Total & LW Sales: penjualan brand per toko selama periode promo & periode LW (query sales toko).
A4: Store Code | B4: Special Offer | D4: Total (19-19 Sep'26) | F4: Stock 7 Sep 2026 | G4: Sellthru | H4: Cont% | I4: LW Sales (12-12 Sep'26) | K4: Growth%
B5: Qty | C5: Amount | D5: Qty | E5: Amount | I5: Qty | J5: Amount
A6: E105 | B6: =SUMIFS(RAW!$B$2:$B$30,RAW!$H$2:$H$30,$A6,RAW!$D$2:$D$30,B$4) | C6: =SUMIFS(RAW!$E$2:$E$30,RAW!$H$2:$H$30,$A6,RAW!$D$2:$D$30,B$4) | D6: 14 | E6: 17930000 | G6: =D6/F6 | H6: =D6/$D$22 | I6: 3 | J6: 6270000 | K6: =E6/J6-1
A7: E310 | B7: =SUMIFS(RAW!$B$2:$B$30,RAW!$H$2:$H$30,$A7,RAW!$D$2:$D$30,B$4) | C7: =SUMIFS(RAW!$E$2:$E$30,RAW!$H$2:$H$30,$A7,RAW!$D$2:$D$30,B$4) | D7: 14 | E7: 23476000 | G7: =D7/F7 | H7: =D7/$D$22 | I7: 5 | J7: 12552000 | K7: =E7/J7-1
A8: E425 | B8: =SUMIFS(RAW!$B$2:$B$30,RAW!$H$2:$H$30,$A8,RAW!$D$2:$D$30,B$4) | C8: =SUMIFS(RAW!$E$2:$E$30,RAW!$H$2:$H$30,$A8,RAW!$D$2:$D$30,B$4) | D8: 5 | E8: 6862000 | G8: =D8/F8 | H8: =D8/$D$22 | I8: 4 | J8: 6692000 | K8: =E8/J8-1
A9: E450 | B9: =SUMIFS(RAW!$B$2:$B$30,RAW!$H$2:$H$30,$A9,RAW!$D$2:$D$30,B$4) | C9: =SUMIFS(RAW!$E$2:$E$30,RAW!$H$2:$H$30,$A9,RAW!$D$2:$D$30,B$4) | D9: 9 | E9: 8212000 | G9: =D9/F9 | H9: =D9/$D$22 | I9: 10 | J9: 11350000 | K9: =E9/J9-1
A10: E460 | B10: =SUMIFS(RAW!$B$2:$B$30,RAW!$H$2:$H$30,$A10,RAW!$D$2:$D$30,B$4) | C10: =SUMIFS(RAW!$E$2:$E$30,RAW!$H$2:$H$30,$A10,RAW!$D$2:$D$30,B$4) | D10: 9 | E10: 7780000 | G10: =D10/F10 | H10: =D10/$D$22 | I10: 12 | J10: 18432000 | K10: =E10/J10-1
A11: E552 | B11: =SUMIFS(RAW!$B$2:$B$30,RAW!$H$2:$H$30,$A11,RAW!$D$2:$D$30,B$4) | C11: =SUMIFS(RAW!$E$2:$E$30,RAW!$H$2:$H$30,$A11,RAW!$D$2:$D$30,B$4) | D11: 22 | E11: 42246000 | G11: =D11/F11 | H11: =D11/$D$22 | I11: 28 | J11: 60504000 | K11: =E11/J11-1
A12: E560 | B12: =SUMIFS(RAW!$B$2:$B$30,RAW!$H$2:$H$30,$A12,RAW!$D$2:$D$30,B$4) | C12: =SUMIFS(RAW!$E$2:$E$30,RAW!$H$2:$H$30,$A12,RAW!$D$2:$D$30,B$4) | D12: 25 | E12: 39521000 | G12: =D12/F12 | H12: =D12/$D$22 | I12: 17 | J12: 28478000 | K12: =E12/J12-1
A13: E630 | B13: =SUMIFS(RAW!$B$2:$B$30,RAW!$H$2:$H$30,$A13,RAW!$D$2:$D$30,B$4) | C13: =SUMIFS(RAW!$E$2:$E$30,RAW!$H$2:$H$30,$A13,RAW!$D$2:$D$30,B$4) | D13: 15 | E13: 22190000 | G13: =D13/F13 | H13: =D13/$D$22 | I13: 13 | J13: 21110000 | K13: =E13/J13-1
A14: E640 | B14: =SUMIFS(RAW!$B$2:$B$30,RAW!$H$2:$H$30,$A14,RAW!$D$2:$D$30,B$4) | C14: =SUMIFS(RAW!$E$2:$E$30,RAW!$H$2:$H$30,$A14,RAW!$D$2:$D$30,B$4) | D14: 8 | E14: 10850000 | G14: =D14/F14 | H14: =D14/$D$22 | I14: 9 | J14: 15202000 | K14: =E14/J14-1
A15: E810 | B15: =SUMIFS(RAW!$B$2:$B$30,RAW!$H$2:$H$30,$A15,RAW!$D$2:$D$30,B$4) | C15: =SUMIFS(RAW!$E$2:$E$30,RAW!$H$2:$H$30,$A15,RAW!$D$2:$D$30,B$4) | D15: 12 | E15: 22300000 | G15: =D15/F15 | H15: =D15/$D$22 | I15: 5 | J15: 7392000 | K15: =E15/J15-1
A16: E815 | B16: =SUMIFS(RAW!$B$2:$B$30,RAW!$H$2:$H$30,$A16,RAW!$D$2:$D$30,B$4) | C16: =SUMIFS(RAW!$E$2:$E$30,RAW!$H$2:$H$30,$A16,RAW!$D$2:$D$30,B$4) | D16: 15 | E16: 25608000 | G16: =D16/F16 | H16: =D16/$D$22 | I16: 8 | J16: 12591300 | K16: =E16/J16-1
A17: E820 | B17: =SUMIFS(RAW!$B$2:$B$30,RAW!$H$2:$H$30,$A17,RAW!$D$2:$D$30,B$4) | C17: =SUMIFS(RAW!$E$2:$E$30,RAW!$H$2:$H$30,$A17,RAW!$D$2:$D$30,B$4) | D17: 33 | E17: 33562000 | G17: =D17/F17 | H17: =D17/$D$22 | I17: 18 | J17: 41820000 | K17: =E17/J17-1
... A21: E950 | B21: =SUMIFS(RAW!$B$2:$B$30,RAW!$H$2:$H$30,$A21,RAW!$D$2:$D$30,B$4) | C21: =SUMIFS(RAW!$E$2:$E$30,RAW!$H$2:$H$30,$A21,RAW!$D$2:$D$30,B$4) | D21: 29 | E21: 47914000 | G21: =D21/F21 | H21: =D21/$D$22 | I21: 17 | J21: 42430000 | K21: =E21/J21-1
A22: GRAND TOTAL | B22: =SUM(B6:B21) | C22: =SUM(C6:C21) | D22: =SUM(D6:D21) | E22: =SUM(E6:E21) | F22: =SUM(F6:F21) | G22: =D22/F22 | H22: =1 | I22: =SUM(I6:I21) | J22: =SUM(J6:J21) | K22: =E22/J22-1
